qksh/__init__.py
qksh/getenv.py
qksh/handle_exception.py
qksh/ihealth_api.py
qksh/logger.py
qksh/logging_wrapper.py
qksh/pidsearch.py
qksh/qksh.py
qksh/sub_daemon.py
qksh/test.py
qksh-1.1.dev14.dist-info/DESCRIPTION.rst
qksh-1.1.dev14.dist-info/METADATA
qksh-1.1.dev14.dist-info/RECORD
qksh-1.1.dev14.dist-info/WHEEL
qksh-1.1.dev14.dist-info/entry_points.txt
qksh-1.1.dev14.dist-info/metadata.json
qksh-1.1.dev14.dist-info/top_level.txt
