Metadata-Version: 2.0
Name: qksh
Version: 1.1.dev14
Summary: A CLI utility working with F5 iHealth GUIfor uploading and downloading files/commands etc.
Home-page: https://github.com/ccorzlol/handy_qkview
Author: Qiang He
Author-email: abc89d@gmail.com
License: MIT
Keywords: qkview ihealth
Platform: UNKNOWN
Classifier: Development Status :: 2 - Pre-Alpha
Classifier: Intended Audience :: Information Technology
Classifier: Topic :: Utilities
Classifier: License :: OSI Approved :: MIT License
Classifier: Operating System :: OS Independent
Classifier: Programming Language :: Python :: 2
Classifier: Programming Language :: Python :: 2.6
Classifier: Programming Language :: Python :: 2.7
Requires-Dist: args (>=0.1.0)
Requires-Dist: clint (>=0.5.1)
Requires-Dist: lockfile (>=0.12.2)
Requires-Dist: logging (>=0.4.9.6)
Requires-Dist: python-daemon (>=2.1.1)
Requires-Dist: requests (>=2.9.1)
Requires-Dist: requests-toolbelt (>=0.6.0)
Requires-Dist: setproctitle (>=1.1.10)
Requires-Dist: wheel (>=0.29.0)
